Metadata-Version: 2.1
Name: waitfornet
Version: 1.0.2
Summary: Module to check whether you are online or not
Home-page: https://github.com/prahladyeri/waitfornet
Author: Prahlad Yeri
Author-email: prahladyeri@yahoo.com
License: MIT
Keywords: internet
Platform: UNKNOWN
Classifier: Programming Language :: Python :: 3
Classifier: License :: OSI Approved :: MIT License
Classifier: Operating System :: OS Independent
